aeroscope/AeroSCOPE.ipynb
aeroscope/__init__.py
aeroscope/aeromaps_front.py
aeroscope/app.py
aeroscope/continental_front.py
aeroscope/continental_level_plots.py
aeroscope/core.py
aeroscope/country_front.py
aeroscope/country_level_plots.py
aeroscope/detailled_front.py
aeroscope/flight_level_plots.py
aeroscope/logo/aeromaps.png
aeroscope/logo/aeroscope.png
aeroscope/passenger_front.py
aeroscope/pax_level_plots.py
aeroscope/plot_files/conti_scatter.csv
aeroscope/plot_files/continental_flows.csv
aeroscope/plot_files/continental_flows_non_dir.csv
aeroscope/plot_files/country_fixed.csv
aeroscope/plot_files/country_flows.csv
aeroscope/plot_files/flights_df.zip
aeroscope/plot_files_os/conti_scatter.csv
aeroscope/plot_files_os/continental_flows.csv
aeroscope/plot_files_os/continental_flows_non_dir.csv
aeroscope/plot_files_os/country_fixed.csv
aeroscope/plot_files_os/country_flows.csv
aeroscope/plot_files_os/flights_df.zip
aeroscope/user_interface.py
aeroscope-0.2.5b0.dist-info/COPYING.txt
aeroscope-0.2.5b0.dist-info/METADATA
aeroscope-0.2.5b0.dist-info/WHEEL
aeroscope-0.2.5b0.dist-info/entry_points.txt
aeroscope-0.2.5b0.dist-info/RECORD
