Metadata-Version: 2.1
Name: aeroscope
Version: 0.2.5b0
Summary: AeroSCOPE: Exploring Aviation Flows
Home-page: https://github.com/AeroMAPS/AeroSCOPE
License: GPL-3.0-only
Keywords: air transport,flight data,fligh emissions
Author: Antoine SALGAS
Author-email: antoine.salgas@isae-supaero.fr
Requires-Python: >=3.8,<3.12
Classifier: License :: OSI Approved :: GNU General Public License v3 (GPLv3)
Classifier: Programming Language :: Python :: 3
Classifier: Programming Language :: Python :: 3.8
Classifier: Programming Language :: Python :: 3.9
Classifier: Programming Language :: Python :: 3.10
Classifier: Programming Language :: Python :: 3.11
Requires-Dist: docutils (>=0.17.1,<0.18.0)
Requires-Dist: ipython (>=8.8.0,<9.0.0)
Requires-Dist: ipyvuetify (>=1.8.10,<2.0.0)
Requires-Dist: ipywidgets (>=8.1.1,<9.0.0)
Requires-Dist: jupyterlab (>=3.6.1,<4.0.0)
Requires-Dist: matplotlib (>=3.6.2,<4.0.0)
Requires-Dist: numpy (>=1.23,<2.0)
Requires-Dist: pandas (>=1.5,<2.0)
Requires-Dist: plotly (>=5.16.1,<6.0.0)
Requires-Dist: voila (==0.4.0)
Requires-Dist: voila-vuetify (==0.6.0)
